comment_style.py
comment_style-0.1.1.dist-info/LICENCE
comment_style-0.1.1.dist-info/METADATA
comment_style-0.1.1.dist-info/WHEEL
comment_style-0.1.1.dist-info/entry_points.txt
comment_style-0.1.1.dist-info/top_level.txt
comment_style-0.1.1.dist-info/RECORD
