Metadata-Version: 2.1
Name: comment-style
Version: 0.1.1
Summary: An opinionated comment style checker.
Home-page: https://github.com/eZanmoto/comment_style
Author: Sean Kelleher
Author-email: ezanmoto@gmail.com
License: MIT
Platform: UNKNOWN
Classifier: License :: OSI Approved :: MIT License
Classifier: Intended Audience :: Developers
Classifier: Operating System :: POSIX :: Linux
Classifier: Programming Language :: Python
Classifier: Programming Language :: Python :: 3
Classifier: Programming Language :: Python :: 3.7
Classifier: Programming Language :: Python :: Implementation :: CPython
Classifier: Programming Language :: Python :: Implementation :: PyPy
Classifier: Topic :: Software Development
Requires-Python: >=3.5.0
Requires-Dist: pyyaml (==5.3.1)
